appollo/__init__.py
appollo/__main__.py
appollo-1.1.1.dist-info/METADATA
appollo-1.1.1.dist-info/WHEEL
appollo-1.1.1.dist-info/entry_points.txt
appollo-1.1.1.dist-info/licenses/LICENSE
appollo-1.1.1.dist-info/RECORD
