Metadata-Version: 2.1
Name: appollo
Version: 1.1.1
Summary: CLI to interact with Appollo, the easy way to setup, build & deploy flutter apps for iOS on Linux, Windows and MacOS
Project-URL: Homepage, https://www.appollo.space
Project-URL: Source, https://github.com/Appollo-CLI/Appollo
Author-email: Appollo <hello@appollo.space>
License: Copyright (c) 2022 Appollo
License-File: LICENSE
Keywords: Flutter,iOS
Classifier: Development Status :: 5 - Production/Stable
Classifier: Environment :: Console
Classifier: License :: OSI Approved :: MIT License
Classifier: Natural Language :: English
Classifier: Operating System :: OS Independent
Classifier: Programming Language :: Python :: 3
Requires-Python: >=3.7.0
Requires-Dist: click==8.0.4
Requires-Dist: paramiko==3.0.0
Requires-Dist: pyjwt==2.4.0
Requires-Dist: qrcode==7.4.2
Requires-Dist: questionary==1.10.0
Requires-Dist: requests==2.27.1
Requires-Dist: rich==11.2.0
Requires-Dist: sseclient-py==1.8.0
